js-stubs/__init__.pyi
webtypy-0.1.7.dist-info/METADATA
webtypy-0.1.7.dist-info/WHEEL
webtypy-0.1.7.dist-info/top_level.txt
webtypy-0.1.7.dist-info/RECORD
