Metadata-Version: 2.1
Name: webtypy
Version: 0.1.7
Summary: This module contains the DOM types for the majority of the web APIs used in a web browser. These can be used by an IDE to give type hinting and completion during the development using DOM apis.
Home-page: https://github.com/pyodide/webtypy
Author: Simone Giacomelli
Author-email: simone.giacomelli@gmail.com
License: MPL 2.0
Provides-Extra: dev
Requires-Dist: build==0.6.0.post1; extra == "dev"
Requires-Dist: twine==3.4.2; extra == "dev"
Requires-Dist: wheel==0.37.0; extra == "dev"
